{"_id":{"$oid":"5bd9aeb7a3caf207f34dcd00"},"username":"Hardik","email":"hj@hj.com","start":"2018-11-06","end":"2018-11-28","oneoff":"on","phone":"0433190011"}
{"_id":{"$oid":"5bda6f5866c75505d98b5566"},"username":"JJ","email":"jj@joshi.com","start":"2018-10-28","end":"2018-11-30","oneoff":null,"phone":"04joshi"}
{"_id":{"$oid":"5bdf80ba249a2c001520e900"},"username":"Ativ Shah","email":"ativshah@yahoo.com","start":"2018-04-06","end":"2019-04-12","oneoff":null,"phone":"416-451-1825"}
{"_id":{"$oid":"5bdf80d8249a2c001520e901"},"username":"Ativ Shah","email":"ativshah@yahoo.com","start":"2018-04-06","end":"2019-04-12","oneoff":"on","phone":"416-451-1825"}
{"_id":{"$oid":"5bdf810a249a2c001520e902"},"username":"Avni Shah","email":"ashah@sslawyers.ca","start":"","end":"","oneoff":"on","phone":"416-706-2888"}
{"_id":{"$oid":"5bdf817d249a2c001520e903"},"username":"Bala Shah","email":"bala@mortgagediligent.com","start":"2018-01-19","end":"2019-01-25","oneoff":"on","phone":"647-830-2104"}
{"_id":{"$oid":"5c693cd7296d9300169d868e"},"username":"Haello","email":"hello@hello.com","start":"2019-01-10","end":"2019-02-28","oneoff":"on","phone":"421-323-2222"}
{"_id":{"$oid":"5c69400c441e65a84abc1592"},"username":"Hardik","email":"hj@hj.com","start":"06-11-18","end":"28-11-18","oneoff":"on","phone":433190011}
{"_id":{"$oid":"5c69400c441e65a84abc1593"},"username":"Ativ Shah","email":"ativshah@yahoo.com","start":"06-04-18","end":"12-04-19","oneoff":"","phone":"416-451-1825"}
{"_id":{"$oid":"5c69400c441e65a84abc1594"},"username":"JJ","email":"jj@joshi.com","start":"28-10-18","end":"30-11-18","oneoff":"","phone":"04joshi"}
{"_id":{"$oid":"5c69400c441e65a84abc1595"},"username":"Avni Shah","email":"ashah@sslawyers.ca","start":"","end":"","oneoff":"on","phone":"416-706-2888"}
{"_id":{"$oid":"5c69400c441e65a84abc1596"},"username":"Ativ Shah","email":"ativshah@yahoo.com","start":"06-04-18","end":"12-04-19","oneoff":"on","phone":"416-451-1825"}
{"_id":{"$oid":"5c69400c441e65a84abc1597"},"username":"Ativ Shah","email":"ativshah4@gmail.com","start":"06-04-18","end":"12-04-19","oneoff":"on","phone":"416-451-1825"}
{"_id":{"$oid":"5c69400c441e65a84abc1598"},"username":"Bala Shah","email":"bala@mortgagediligent.com","start":"19-01-18","end":"25-01-19","oneoff":"on","phone":"647-830-2104"}
{"_id":{"$oid":"5c69400c441e65a84abc1599"},"username":"Avni Shah","email":"ashah@sslawyers.ca","start":"","end":"","oneoff":"on","phone":"416-818-4000"}
{"_id":{"$oid":"5c69400c441e65a84abc159a"},"username":"Balkrishna Shah","email":"bala@mortgagediligent.com","start":"01-02-19","end":"31-01-20","oneoff":"on","phone":"647-830-2104"}
{"_id":{"$oid":"5c69400c441e65a84abc159b"},"username":"Hiral Patel","email":"hiral1.patel@cibc.com","start":"26-10-18","end":"01-11-19","oneoff":"on","phone":"647-402-6221"}
{"_id":{"$oid":"5c69400c441e65a84abc159c"},"username":"Mushtaqbhai","email":"","start":"","end":"","oneoff":"on","phone":"416-289-2836"}
{"_id":{"$oid":"5c69400c441e65a84abc159d"},"username":"Paresh Peshva","email":"ppeshva23@hotmail.com","start":"31-08-18","end":"08-03-19","oneoff":"on","phone":"416-302-4531"}
{"_id":{"$oid":"5c69400c441e65a84abc159e"},"username":"Haello","email":"hello@hello.com","start":"10-01-19","end":"28-02-19","oneoff":"on","phone":"421-323-2222"}
{"_id":{"$oid":"5c69400c441e65a84abc159f"},"username":"Vinayak Patel","email":"info@vinayakpatel.realtor","start":"13-04-18","end":"19-04-19","oneoff":"on","phone":"647-222-3549"}
{"_id":{"$oid":"5c69400c441e65a84abc15a0"},"username":"Amit/Komal Shah","email":"amit4gtahomes@gmail.com","start":"18-01-19","end":"24-01-20","oneoff":"on","phone":"647-995-5640"}
{"_id":{"$oid":"5c69400c441e65a84abc15a1"},"username":"Swapnil Patel","email":"swapnil.patel@scotiabank.com","start":"01-02-19","end":"24-01-20","oneoff":"on","phone":"437-775-5905"}
{"_id":{"$oid":"5c69400c441e65a84abc15a2"},"username":"Bhavin Shah","email":"bshah72@gmail.com","start":"06-04-18","end":"12-04-19","oneoff":"on","phone":"416-818-1972"}
{"_id":{"$oid":"5c69400c441e65a84abc15a3"},"username":"Ativ Shah (2)","email":"ativshah4@gmail.com","start":"06-04-18","end":"12-04-19","oneoff":"on","phone":"416-451-1825"}
{"_id":{"$oid":"5c69400c441e65a84abc15a4"},"username":"Niraj Pancholi","email":"ncpancholi@gmail.com","start":"","end":"","oneoff":"on","phone":"647-866-2790"}
{"_id":{"$oid":"5c69400c441e65a84abc15a5"},"username":"Nirwang Patel","email":"nirwang9@gmail.com","start":"09-02-18","end":"08-02-19","oneoff":"on","phone":"647-896-8246"}
{"_id":{"$oid":"5c69400c441e65a84abc15a6"},"username":"Dr. Salim Kapadia","email":"info@drsalimkapadiadental.com","start":"02-11-18","end":"01-11-19","oneoff":"on","phone":"416-321-3268"}
{"_id":{"$oid":"5c69400c441e65a84abc15a7"},"username":"Arnik Jewelers","email":"jitesh@arnikjewellers.com","start":"26-10-18","end":"03-05-19","oneoff":"on","phone":"416-788-1635"}
{"_id":{"$oid":"5c69400c441e65a84abc15a8"},"username":"Big's Creation Photo Studio","email":"bigfilmsltd@gmail.com","start":"23-11-18","end":"01-03-19","oneoff":"on","phone":"647-983-2447"}
{"_id":{"$oid":"5c69400c441e65a84abc15a9"},"username":"Chapel Ridge Funeral Home","email":"info@chapelridgefh.com","start":"04-01-19","end":"27-12-19","oneoff":"on","phone":"416-993-0826"}
{"_id":{"$oid":"5c69400c441e65a84abc15aa"},"username":"Economical Financial Services","email":"hshah@economicalfinancial.com","start":"11-01-19","end":"28-06-19","oneoff":"on","phone":"416-522-1676"}
{"_id":{"$oid":"5c69400c441e65a84abc15ab"},"username":"Imperial Pest Control","email":"info@imperialpestcontrol.ca","start":"13-04-18","end":"19-04-19","oneoff":"on","phone":"416-837-1820"}
{"_id":{"$oid":"5c69400c441e65a84abc15ac"},"username":"Kanan Mehta","email":"kanan07_m@yahoo.com","start":"27-04-18","end":"19-04-19","oneoff":"on","phone":"416-878-0139"}
{"_id":{"$oid":"5c69400c441e65a84abc15ad"},"username":"Sandeep Prabhakar","email":"sandeepp@mortgagediligent.com","start":"","end":"","oneoff":"on","phone":"416-720-3536"}
{"_id":{"$oid":"5c69400c441e65a84abc15ae"},"username":"Bhavik Vyas","email":"bhavik@teamsabharwal.com","start":"23-03-18","end":"29-03-19","oneoff":"on","phone":"647-542-9549"}
{"_id":{"$oid":"5c69400c441e65a84abc15af"},"username":"Aisha Munawar","email":"aisham@rumanek.com","start":"17-08-18","end":"11-01-19","oneoff":"off","phone":"416-428-2165"}
{"_id":{"$oid":"5c69400c441e65a84abc15b0"},"username":"Continental Motors","email":"continentalmotorsinc@gmail.com","start":"","end":"","oneoff":"on","phone":"416-575-1277"}
{"_id":{"$oid":"5c69400c441e65a84abc15b1"},"username":"Dharmendra Parmar","email":"dharmendra.parmar@sunlife.com","start":"01-02-19","end":"19-07-19","oneoff":"on","phone":"905-763-8188"}
{"_id":{"$oid":"5c69400c441e65a84abc15b2"},"username":"Geetanjali","email":"","start":"","end":"","oneoff":"on","phone":"416-617-0790"}
{"_id":{"$oid":"5c69400c441e65a84abc15b3"},"username":"India Puja Hut","email":"rishi_643@rogers.com","start":"01-03-19","end":"","oneoff":"off","phone":"647-220-3771"}
{"_id":{"$oid":"5c69400c441e65a84abc15b4"},"username":"Jignesh Dave","email":"daveinvestment2015@gmail.com","start":"09-03-18","end":"15-03-19","oneoff":"on","phone":"647-978-9124"}
{"_id":{"$oid":"5c69400c441e65a84abc15b5"},"username":"Nirav Bhatt - Aastha Lawyers","email":"info@aasthalaw.ca","start":"16-11-18","end":"22-02-19","oneoff":"on","phone":"905-564-8200"}
{"_id":{"$oid":"5c69400c441e65a84abc15b6"},"username":"Nirav Brahmbhatt","email":"nirav.insurance@gmail.com","start":"01-02-19","end":"31-01-20","oneoff":"on","phone":"647-938-5147"}
{"_id":{"$oid":"5c69400c441e65a84abc15b7"},"username":"R \u0026 D Painting","email":"rndpainting@yahoo.ca","start":"22-06-19","end":"28-06-19","oneoff":"on","phone":"416-817-6221"}
{"_id":{"$oid":"5c69400c441e65a84abc15b8"},"username":"Ramesh Patel","email":"ramesh4insurance@gmail.com","start":"","end":"","oneoff":"on","phone":"416-356-6992"}
{"_id":{"$oid":"5c69400c441e65a84abc15b9"},"username":"Upendra Trivedi","email":"upendra@trivediassociates.ca","start":"","end":"","oneoff":"on","phone":"647-839-6733"}
{"_id":{"$oid":"5c69400c441e65a84abc15ba"},"username":"Nanak Flights","email":"mkapoor@nanakflights.com","start":"09-02-18","end":"15-02-19","oneoff":"on","phone":"905-456-9977"}
{"_id":{"$oid":"5c69400c441e65a84abc15bb"},"username":"All Link Travel Services","email":"alt9052397711@gmail.com","start":"04-01-19","end":"29-03-19","oneoff":"on","phone":"416-670-7562"}
{"_id":{"$oid":"5c69400c441e65a84abc15bc"},"username":"Hiren Patel","email":"hiren.patel@ams.house","start":"18-01-19","end":"12-07-19","oneoff":"on","phone":"647-219-5493"}
{"_id":{"$oid":"5c69400c441e65a84abc15bd"},"username":"Krishan Prabhakar","email":"krishan@talktomycpa.com","start":"04-01-19","end":"26-04-19","oneoff":"on","phone":"647-294-4000"}
{"_id":{"$oid":"5c69400c441e65a84abc15be"},"username":"Sagar Parikh","email":"sparikh@allstate.ca","start":"04-01-19","end":"21-06-19","oneoff":"on","phone":"416-770-3123"}
{"_id":{"$oid":"5c69400c441e65a84abc15bf"},"username":"Vatica","email":"vaticacanada@yahoo.ca","start":"02-03-18","end":"22-02-19","oneoff":"on","phone":"647-428-3248"}
{"_id":{"$oid":"5c69400c441e65a84abc15c0"},"username":"Webmob Technologies","email":"vijal@webmobitecnologies.info","start":"","end":"","oneoff":"on","phone":"647-963-4870"}
{"_id":{"$oid":"5c69400c441e65a84abc15c1"},"username":"Brampton Crematorium","email":"homekey123@gmail.com","start":"25-01-19","end":"12-07-19","oneoff":"on","phone":"905-458-2222"}
{"_id":{"$oid":"5c69400c441e65a84abc15c2"},"username":"Nanak Flights (2)","email":"mkapoor@nanakflights.com","start":"01-02-19","end":"07-02-20","oneoff":"on","phone":"905-456-9977"}
{"_id":{"$oid":"5c69400c441e65a84abc15c3"},"username":"Sky Route Travel Services","email":"naga@skyroutetravel.com","start":"13-07-18","end":"12-04-19","oneoff":"on","phone":"416-439-4000"}
{"_id":{"$oid":"5c69400c441e65a84abc15c4"},"username":"Super Vision Optical","email":"supervision1901@gmail.com","start":"25-06-18","end":"21-09-18","oneoff":"off","phone":"416-245-3418"}
